apsniper0673_datahandler-0.1.16.dist-info/licenses/LICENSE
mydatahandler/__init__.py
mydatahandler/api.py
mydatahandler/simple_api.py
mydatahandler/test_api.py
mydatahandler/handler/__init__.py
mydatahandler/handler/singleday_data_handler.py
mydatahandler/handler/stock_data_handler.py
mydatahandler/handler/functions/__init__.py
mydatahandler/handler/functions/calculate_limit.py
mydatahandler/handler/functions/crawler_krx.py
mydatahandler/handler/functions/get_recent_df.py
mydatahandler/handler/functions/remove_unnecessary.py
mydatahandler/handler/functions/update_upsert_df.py
mydatahandler/utility/__init__.py
mydatahandler/utility/crawler/__init__.py
mydatahandler/utility/crawler/naver.py
mydatahandler/utility/crawler/nxt.py
mydatahandler/utility/db/sql.py
apsniper0673_datahandler-0.1.16.dist-info/METADATA
apsniper0673_datahandler-0.1.16.dist-info/WHEEL
apsniper0673_datahandler-0.1.16.dist-info/top_level.txt
apsniper0673_datahandler-0.1.16.dist-info/RECORD
