Metadata-Version: 2.4
Name: apsniper0673_datahandler
Version: 0.1.16
Summary: My stock data handler for APSniper0673
Author: apsniper0673
Requires-Python: >=3.8
License-File: LICENSE
Dynamic: license-file
